fbpcp/__init__.py
fbpcp/cloud/__init__.py
fbpcp/decorator/__init__.py
fbpcp/decorator/error_handler.py
fbpcp/decorator/metrics.py
fbpcp/entity/__init__.py
fbpcp/entity/certificate_request.py
fbpcp/entity/cloud_cost.py
fbpcp/entity/cloud_provider.py
fbpcp/entity/cluster_instance.py
fbpcp/entity/container_definition.py
fbpcp/entity/container_insight.py
fbpcp/entity/container_instance.py
fbpcp/entity/container_metadata.py
fbpcp/entity/container_permission.py
fbpcp/entity/container_type.py
fbpcp/entity/file_information.py
fbpcp/entity/firewall_ruleset.py
fbpcp/entity/insight.py
fbpcp/entity/log_event.py
fbpcp/entity/pce.py
fbpcp/entity/pce_compute.py
fbpcp/entity/pce_network.py
fbpcp/entity/policy_settings_config.py
fbpcp/entity/policy_statement.py
fbpcp/entity/route_table.py
fbpcp/entity/secret.py
fbpcp/entity/subnet.py
fbpcp/entity/vpc_instance.py
fbpcp/entity/vpc_peering.py
fbpcp/error/__init__.py
fbpcp/error/pcp.py
fbpcp/error/mapper/__init__.py
fbpcp/error/mapper/aws.py
fbpcp/error/mapper/gcp.py
fbpcp/error/mapper/k8s.py
fbpcp/gateway/__init__.py
fbpcp/gateway/aws.py
fbpcp/gateway/cloudwatch.py
fbpcp/gateway/costexplorer.py
fbpcp/gateway/ec2.py
fbpcp/gateway/ecs.py
fbpcp/gateway/gcp.py
fbpcp/gateway/gcs.py
fbpcp/gateway/kms.py
fbpcp/gateway/s3.py
fbpcp/gateway/secrets_manager.py
fbpcp/mapper/__init__.py
fbpcp/mapper/aws.py
fbpcp/metrics/__init__.py
fbpcp/metrics/emitter.py
fbpcp/metrics/getter.py
fbpcp/service/__init__.py
fbpcp/service/billing.py
fbpcp/service/billing_aws.py
fbpcp/service/container.py
fbpcp/service/container_aws.py
fbpcp/service/insights.py
fbpcp/service/log.py
fbpcp/service/log_cloudwatch.py
fbpcp/service/onedocker.py
fbpcp/service/pce.py
fbpcp/service/pce_aws.py
fbpcp/service/policy_validation.py
fbpcp/service/policy_validation_aws.py
fbpcp/service/secrets_manager.py
fbpcp/service/secrets_manager_aws.py
fbpcp/service/storage.py
fbpcp/service/storage_gcs.py
fbpcp/service/storage_s3.py
fbpcp/util/__init__.py
fbpcp/util/arg_builder.py
fbpcp-0.6.4.dist-info/LICENSE
fbpcp-0.6.4.dist-info/METADATA
fbpcp-0.6.4.dist-info/WHEEL
fbpcp-0.6.4.dist-info/top_level.txt
fbpcp-0.6.4.dist-info/RECORD
