Metadata-Version: 2.1
Name: fbpcp
Version: 0.6.4
Summary: Facebook Private Computation Platform
Home-page: https://github.com/facebookresearch/fbpcp
Author: Facebook
Author-email: researchtool-help@fb.com
Requires-Python: >=3.8
License-File: LICENSE
Requires-Dist: boto3 ==1.18.57
Requires-Dist: urllib3 ==1.26.19
Requires-Dist: dataclasses-json ==0.5.2
Requires-Dist: pyyaml ==5.4.1
Requires-Dist: tqdm ==4.66.3
Requires-Dist: google-cloud-storage ==1.30.0
Requires-Dist: docopt ==0.6.2
Requires-Dist: schema ==0.7.5
Requires-Dist: psutil ==5.8.0
Requires-Dist: click ==7.1.2
Requires-Dist: kubernetes ==12.0.1
